agent_queues/__init__.py
agent_queues/agent_queue.py
agent_queues/agent_queue_manager.py
agent_queues/agent_queue_report.py
agent_queues/queue_service.proto
agent_queues/queue_service_pb2.py
agent_queues/queue_service_pb2_grpc.py
agent_queues/retry_interceptor.py
agent_queues/settings.py
agent_queues/config/grpc.yaml
examples/advanced_usage.py
examples/basic_usage.py
examples/complete_workflow.py
examples/get_queue_example.py
examples/report_example.py
examples/view_proto_example.py
queues_manager-1.0.10.dist-info/licenses/LICENSE
scripts/__init__.py
scripts/build.py
scripts/check_build.py
scripts/check_package_contents.py
scripts/generate_grpc.py
scripts/publish.py
scripts/pypi_credentials.py
scripts/start_celery_worker.py
scripts/start_server.py
scripts/sync_config.py
scripts/test_installed_proto.py
scripts/verify_package.py
scripts/verify_proto_in_package.py
server/__init__.py
server/settings.py
server/celery/__init__.py
server/celery/app.py
server/celery/celery_config.py
server/celery/handlers.py
server/grpc/__init__.py
server/grpc/service.py
server/redis/__init__.py
server/redis/queue_manager.py
tests/__init__.py
tests/conftest.py
tests/test_client_wrapper.py
tests/test_comprehensive.py
tests/test_grpc_reconnect.py
tests/test_idempotency.py
tests/test_integration.py
tests/test_queue_management.py
tests/test_queue_report.py
tests/test_task_operations.py
tests/test_task_priority.py
tests/test_task_queries.py
queues_manager-1.0.10.dist-info/METADATA
queues_manager-1.0.10.dist-info/WHEEL
queues_manager-1.0.10.dist-info/top_level.txt
queues_manager-1.0.10.dist-info/RECORD
