Metadata-Version: 2.4
Name: queues-manager
Version: 1.0.10
Summary: A private task queue system for agents using Redis + Celery with gRPC interface (Client Package)
Author-email: NightSailingShip <149816081+NightSailingShip@users.noreply.github.com>
License: MIT
Project-URL: Homepage, https://github.com/NightSailingShip/queues
Project-URL: Documentation, https://github.com/NightSailingShip/queues#readme
Project-URL: Repository, https://github.com/NightSailingShip/queues
Project-URL: Issues, https://github.com/NightSailingShip/queues/issues
Keywords: task-queue,celery,redis,grpc,agent,distributed,client
Classifier: Development Status :: 4 - Beta
Classifier: Intended Audience :: Developers
Classifier: Programming Language :: Python :: 3
Classifier: Programming Language :: Python :: 3.12
Classifier: Topic :: Software Development :: Libraries :: Python Modules
Classifier: Topic :: System :: Distributed Computing
Requires-Python: >=3.12
License-File: LICENSE
Requires-Dist: grpcio>=1.60.0
Requires-Dist: grpcio-tools>=1.60.0
Requires-Dist: protobuf>=4.25.0
Requires-Dist: pyyaml>=6.0.0
Provides-Extra: dev
Requires-Dist: pytest>=7.4.0; extra == "dev"
Requires-Dist: build>=1.0.0; extra == "dev"
Requires-Dist: twine>=4.0.0; extra == "dev"
Dynamic: license-file
